LICENSE
MANIFEST.in
README.rst
pavement.py
requirements-dev.txt
requirements.txt
setup.py
tox.ini
docs/Makefile
docs/make.bat
docs/source/README
docs/source/api.rst
docs/source/conf.py
docs/source/index.rst
docs/source/_static/.gitkeep
ecs/__init__.py
ecs/exceptions.py
ecs/managers.py
ecs/metadata.py
ecs/models.py
ecs.egg-info/PKG-INFO
ecs.egg-info/SOURCES.txt
ecs.egg-info/dependency_links.txt
ecs.egg-info/not-zip-safe
ecs.egg-info/requires.txt
ecs.egg-info/top_level.txt
tests/__init__.py
tests/helpers.py
tests/test_managers.py