Metadata-Version: 1.1
Name: ecs
Version: 0.1
Summary: An entity/component system library for games
Home-page: https://github.com/seanfisk/ecs
Author: Sean Fisk
Author-email: sean@seanfisk.com
License: UNKNOWN
Platform: UNKNOWN
Classifier: Development Status :: 3 - Alpha
Classifier: Intended Audience :: Developers
Classifier: License :: OSI Approved :: MIT License
Classifier: Natural Language :: English
Classifier: Operating System :: OS Independent
Classifier: Programming Language :: Python :: 2.6
Classifier: Programming Language :: Python :: 2.7
Classifier: Programming Language :: Python :: 3.3
Classifier: Programming Language :: Python :: Implementation :: PyPy
Classifier: Topic :: Games/Entertainment
Classifier: Topic :: Software Development :: Libraries :: Application Frameworks
